climpie/__init__.py
climpie/operations.py
climpie/py.typed
climpie-0.1.0.dist-info/METADATA
climpie-0.1.0.dist-info/WHEEL
climpie-0.1.0.dist-info/RECORD
