Metadata-Version: 2.1
Name: climpie
Version: 0.1.0
Summary: Tools for calculating entities' emissions budgets and associated emissions pathways.
Author: Zebedee Nicholls
Author-email: zebedee.nicholls@climate-resource.com
Requires-Python: >=3.9,<4.0
Classifier: Programming Language :: Python :: 3
Classifier: Programming Language :: Python :: 3.9
Classifier: Programming Language :: Python :: 3.10
Classifier: Programming Language :: Python :: 3.11
Provides-Extra: notebooks
Provides-Extra: plots
Requires-Dist: matplotlib (>=3.7.1,<4.0.0) ; extra == "plots"
Requires-Dist: notebook (>=6.5.3,<7.0.0) ; extra == "notebooks"
